{
  "type": "meta",
  "id": "levels",

  "en": [
    "Honey Bee Level",
    "Wild Hare Level",
    "Warthog Level",
    "Springbok Level",
    "Zebra Level",
    "Lion Level",
    "Rhino Level",
    "Elephant Level"
  ],

  "zu": [
    "Honey Bee Level",
    "Wild Hare Level",
    "Warthog Level",
    "Springbok Level",
    "Zebra Level",
    "Lion Level",
    "Rhino Level",
    "Elephant Level"
  ],

  "af": [
    "Honey Bee Level",
    "Wild Hare Level",
    "Warthog Level",
    "Springbok Level",
    "Zebra Level",
    "Lion Level",
    "Rhino Level",
    "Elephant Level"
  ],

  "xh": [
    "Honey Bee Level",
    "Wild Hare Level",
    "Warthog Level",
    "Springbok Level",
    "Zebra Level",
    "Lion Level",
    "Rhino Level",
    "Elephant Level"
  ]
}